[
  {
    "id": "n101",
    "createdAt": 1112222,
    "type": "NoteTxt",
    "isPinned": true,
    "style": { "backgroundColor": "#ffffff" },
    "info": {
      "txt": "I had a weird dream where the code on my computer screen came to life, glowing with an eerie blue light and rearranging itself into intricate patterns and shapes. It was both fascinating and unsettling.",
      "title": "My Dream"
    }
  },
  {
    "id": "n105",
    "createdAt": 1112244,
    "type": "NoteTxt",
    "isPinned": false,
    "style": { "backgroundColor": "#ffffff" },
    "info": {
      "txt": "Taizu - Known for its upscale Asian fusion cuisine and stylish decor, Taizu is a must-visit spot for foodies in Tel Aviv. The restaurant offers an extensive menu of creative dishes, such as seafood ceviche, beef tartare with chili, and crispy pork belly.",
      "title": "Best Restaurant"
    }
  },
  {
    "id": "n104",
    "createdAt": 1112255,
    "type": "NoteTxt",
    "isPinned": true,
    "style": { "backgroundColor": "#ffffff" },
    "info": { "txt": "NoFreeInternetHere", "title": "WIFI password" }
  },
  {
    "id": "n103",
    "type": "NoteImg",
    "isPinned": false,
    "info": {
      "url": "https://images.unsplash.com/photo-1599270606287-331b4f5d0e02?ixlib=rb-4.0.3&ixid=MnwxMjA3fDB8MHxzZWFyY2h8NHx8c3Vuc2hpbmV8ZW58MHx8MHx8&w=1000&q=80",
      "title": "Bobi and Me"
    },
    "style": { "backgroundColor": "#ffffff" }
  },
  {
    "id": "n102",
    "type": "NoteTodos",
    "isPinned": false,
    "style": { "backgroundColor": "#ffffff" },
    "info": {
      "title": "Get my stuff together",
      "todos": [
        {
          "txt": "Driving license",
          "doneAt": null
        },
        { "txt": "Coding power", "doneAt": 187111111 },
        {
          "txt": "Sleep",
          "doneAt": null
        },
        {
          "txt": "Meet people",
          "doneAt": null
        }
      ]
    }
  },
  {
    "id": "n106",
    "type": "NoteVideo",
    "isPinned": false,
    "info": {
      "url": "http://commondatastorage.googleapis.com/gtv-videos-bucket/sample/ForBiggerFun.mp4",
      "title": "Danielush"
    },
    "style": { "backgroundColor": "#ffffff" }
  },
  {
    "id": "n107",
    "type": "NoteAudio",
    "isPinned": false,
    "info": {
      "url": "https://commondatastorage.googleapis.com/codeskulptor-demos/riceracer_assets/music/start.ogg",
      "title": "Audio"
    },
    "style": { "backgroundColor": "#ffffff" }
  },
  {
    "id": "n108",
    "type": "NoteImg",
    "isPinned": true,
    "info": {
      "url": "https://cdn.pixabay.com/photo/2016/09/08/21/09/piano-1655558_1280.jpg",
      "title": "My Piano"
    },
    "style": { "backgroundColor": "#ffffff" }
  }
]
